ADMIRE_maastricht/ADMIRE.py
ADMIRE_maastricht/ADMIRE_highres2.png
ADMIRE_maastricht/ADMIRE_icon.ico
ADMIRE_maastricht/ADMIREv1.py
ADMIRE_maastricht/MatplotlibWidget5.py
ADMIRE_maastricht/Qt5file.py
ADMIRE_maastricht/Resource_rc5.py
ADMIRE_maastricht/__init__.py
ADMIRE_maastricht/__main__.py
ADMIRE_maastricht/command_line.py
ADMIRE_maastricht/models/Human iPSC-CM (Kernik-2019).mmt
ADMIRE_maastricht-1.1.1.1.dist-info/DESCRIPTION.rst
ADMIRE_maastricht-1.1.1.1.dist-info/METADATA
ADMIRE_maastricht-1.1.1.1.dist-info/RECORD
ADMIRE_maastricht-1.1.1.1.dist-info/WHEEL
ADMIRE_maastricht-1.1.1.1.dist-info/entry_points.txt
ADMIRE_maastricht-1.1.1.1.dist-info/metadata.json
ADMIRE_maastricht-1.1.1.1.dist-info/top_level.txt
