Metadata-Version: 2.0
Name: ADMIRE-maastricht
Version: 1.1.1.1
Summary: ADMIRE_maastricht
Home-page: http://www.jordiheijman.net/
Author: UNKNOWN
Author-email: UNKNOWN
License: UNKNOWN
Platform: UNKNOWN
Requires-Dist: myokit
